llama_index/tools/dappier/__init__.py
llama_index/tools/dappier/ai_recommendations/__init__.py
llama_index/tools/dappier/ai_recommendations/base.py
llama_index/tools/dappier/real_time_search/__init__.py
llama_index/tools/dappier/real_time_search/base.py
llama_index_tools_dappier-0.4.1.dist-info/METADATA
llama_index_tools_dappier-0.4.1.dist-info/WHEEL
llama_index_tools_dappier-0.4.1.dist-info/licenses/LICENSE
llama_index_tools_dappier-0.4.1.dist-info/RECORD
