Metadata-Version: 2.4
Name: llama-index-tools-dappier
Version: 0.4.1
Summary: llama-index tools dappier integration
Author-email: Your Name <you@example.com>
License-Expression: MIT
License-File: LICENSE
Requires-Python: <4.0,>=3.9
Requires-Dist: dappier<0.4,>=0.3.4
Requires-Dist: llama-index-core<0.15,>=0.13.0
